[{"slot_id":1, "status":"NOT OCCUPIED"},
 {"slot_id":2, "status":"NOT OCCUPIED"},
 {"slot_id":3, "status":"NOT OCCUPIED"},
 {"slot_id":4, "status":"NOT OCCUPIED"},
 {"slot_id":5, "status":"NOT OCCUPIED"},
 {"slot_id":6, "status":"NOT OCCUPIED"},
 {"slot_id":7, "status":"NOT OCCUPIED"},
 {"slot_id":8, "status":"NOT OCCUPIED"},
 {"slot_id":9, "status":"NOT OCCUPIED"},
 {"slot_id":10, "status":"NOT OCCUPIED"},
 {"slot_id":11, "status":"NOT OCCUPIED"},
 {"slot_id":12, "status":"NOT OCCUPIED"},
 {"slot_id":13, "status":"NOT OCCUPIED"},
 {"slot_id":14, "status":"NOT OCCUPIED"},
 {"slot_id":15, "status":"NOT OCCUPIED"}]